gitdb/__init__.py
gitdb/client.py
gitdb/connection.py
gitdb/types.py
gitdb_client-1.0.0.dist-info/METADATA
gitdb_client-1.0.0.dist-info/WHEEL
gitdb_client-1.0.0.dist-info/top_level.txt
gitdb_client-1.0.0.dist-info/RECORD
