Metadata-Version: 2.4
Name: gitdb-client
Version: 1.0.0
Summary: Official Python client for GitDB - GitHub-backed NoSQL database
Home-page: https://github.com/karthikeyanV2K/GitDB
Author: AFOT Team
Author-email: team@afot.com
Maintainer: karthikeyanV2K
Maintainer-email: karthikeyan@afot.com
Project-URL: Bug Reports, https://github.com/karthikeyanV2K/GitDB/issues
Project-URL: Source, https://github.com/karthikeyanV2K/GitDB
Project-URL: Documentation, https://github.com/karthikeyanV2K/GitDB/tree/main/sdk/python
Keywords: gitdb,database,nosql,github,client,sdk,python,async
Classifier: Development Status :: 4 - Beta
Classifier: Intended Audience :: Developers
Classifier: License :: OSI Approved :: MIT License
Classifier: Operating System :: OS Independent
Classifier: Programming Language :: Python :: 3
Classifier: Programming Language :: Python :: 3.8
Classifier: Programming Language :: Python :: 3.9
Classifier: Programming Language :: Python :: 3.10
Classifier: Programming Language :: Python :: 3.11
Classifier: Programming Language :: Python :: 3.12
Classifier: Topic :: Database
Classifier: Topic :: Software Development :: Libraries :: Python Modules
Requires-Python: >=3.8
Requires-Dist: aiohttp>=3.8.0
Requires-Dist: requests>=2.25.0
Requires-Dist: pydantic>=2.0.0
Provides-Extra: dev
Requires-Dist: pytest>=7.0.0; extra == "dev"
Requires-Dist: pytest-asyncio>=0.21.0; extra == "dev"
Requires-Dist: pytest-cov>=4.0.0; extra == "dev"
Requires-Dist: black>=23.0.0; extra == "dev"
Requires-Dist: isort>=5.12.0; extra == "dev"
Requires-Dist: mypy>=1.0.0; extra == "dev"
Requires-Dist: flake8>=6.0.0; extra == "dev"
Provides-Extra: pandas
Requires-Dist: pandas>=1.5.0; extra == "pandas"
Provides-Extra: jupyter
Requires-Dist: jupyter>=1.0.0; extra == "jupyter"
Requires-Dist: ipywidgets>=8.0.0; extra == "jupyter"
Dynamic: author
Dynamic: author-email
Dynamic: classifier
Dynamic: description
Dynamic: description-content-type
Dynamic: home-page
Dynamic: keywords
Dynamic: maintainer
Dynamic: maintainer-email
Dynamic: project-url
Dynamic: provides-extra
Dynamic: requires-dist
Dynamic: requires-python
Dynamic: summary
